pyinstxtractorcn/__init__.py
pyinstxtractorcn/cli.py
pyinstxtractorcn-1.1.0.dist-info/METADATA
pyinstxtractorcn-1.1.0.dist-info/WHEEL
pyinstxtractorcn-1.1.0.dist-info/entry_points.txt
pyinstxtractorcn-1.1.0.dist-info/top_level.txt
pyinstxtractorcn-1.1.0.dist-info/RECORD
