Metadata-Version: 2.4
Name: pyinstxtractorcn
Version: 1.1.0
Summary: 解包 PyInstaller 生成的 .exe 程序（中文版）
Home-page: https://github.com/jzm3/pyinstxtractorCN
Author: JZM
Author-email: pyinstxtractorcn@outlook.com
License: GPL-3.0-or-later
Project-URL: 文档, https://github.com/jzm3/pyinstxtractorCN/wiki
Project-URL: 源码, https://github.com/jzm3/pyinstxtractorCN
Project-URL: 更新日志, https://github.com/jzm3/pyinstxtractorCN/releases
Project-URL: 问题追踪, https://github.com/jzm3/pyinstxtractorCN/issues
Classifier: Development Status :: 4 - Beta
Classifier: Intended Audience :: Developers
Classifier: Topic :: Software Development :: Disassemblers
Classifier: Operating System :: OS Independent
Classifier: Natural Language :: Chinese (Simplified)
Classifier: Programming Language :: Python :: 3
Classifier: Programming Language :: Python :: 3.6
Classifier: Programming Language :: Python :: 3.7
Classifier: Programming Language :: Python :: 3.8
Classifier: Programming Language :: Python :: 3.9
Classifier: Programming Language :: Python :: 3.10
Classifier: Programming Language :: Python :: 3.11
Classifier: Programming Language :: Python :: 3.12
Requires-Python: >=3.6
Dynamic: author
Dynamic: author-email
Dynamic: classifier
Dynamic: description
Dynamic: description-content-type
Dynamic: home-page
Dynamic: license
Dynamic: project-url
Dynamic: requires-python
Dynamic: summary
